MANIFEST.in
README.md
requirements.txt
setup.py
gitanalysis/__init__.py
gitanalysis.egg-info/PKG-INFO
gitanalysis.egg-info/SOURCES.txt
gitanalysis.egg-info/dependency_links.txt
gitanalysis.egg-info/entry_points.txt
gitanalysis.egg-info/requires.txt
gitanalysis.egg-info/top_level.txt
gitanalysis/app/__init__.py
gitanalysis/app/cli.py
gitanalysis/domain/__init__.py
gitanalysis/domain/changelog.py
gitanalysis/domain/effort_by_author.py
gitanalysis/domain/git.py
gitanalysis/domain/stdin.py
gitanalysis/domain/stdout.py
gitanalysis/infrastructure/__init__.py
gitanalysis/infrastructure/git_shell.py
gitanalysis/infrastructure/stdin_click.py
gitanalysis/infrastructure/stdout_click.py
gitanalysis_tests/acceptances/__init__.py
gitanalysis_tests/acceptances/test_cli.py
gitanalysis_tests/acceptances/fixtures/__init__.py
gitanalysis_tests/spikes/__init__.py
gitanalysis_tests/spikes/changelog_run.py
gitanalysis_tests/units/__init__.py
gitanalysis_tests/units/domain/__init__.py
gitanalysis_tests/units/domain/test_changelog.py