Metadata-Version: 2.1
Name: gitanalysis
Version: 1.0.5
Summary: UNKNOWN
Home-page: https://github.com/FabienArcellier/gitanalysis
Author: Fabien Arcellier
Author-email: fabien.arcellier@gmail.com
License: MIT license
Platform: UNKNOWN
Classifier: Programming Language :: Python :: 2.7
Classifier: Programming Language :: Python :: 3.6
Classifier: License :: OSI Approved :: MIT License
Classifier: Operating System :: OS Independent
Classifier: Intended Audience :: Developers
Classifier: Environment :: Console
Classifier: Development Status :: 5 - Production/Stable
Provides-Extra: dev
